akaudit/__init__.py
akaudit/audit.py
akaudit/authorized_keys.py
akaudit/clidriver.py
akaudit/keytools.py
akaudit/userinput.py
akaudit-0.2.1.data/scripts/akaudit
akaudit-0.2.1.dist-info/LICENSE.txt
akaudit-0.2.1.dist-info/METADATA
akaudit-0.2.1.dist-info/WHEEL
akaudit-0.2.1.dist-info/top_level.txt
akaudit-0.2.1.dist-info/RECORD
