Metadata-Version: 2.1
Name: akaudit
Version: 0.2.1
Summary: Audit who has SSH access to your user homes via authorized_keys.
Home-page: https://github.com/flaccid/akaudit
Author: Chris Fordham
Author-email: chris@fordham-nagy.id.au
License: Apache 2.0
Download-URL: https://github.com/flaccid/akaudit/tarball/v0.2.1
Platform: UNKNOWN
Requires-Dist: paramiko
Requires-Dist: colorama
Requires-Dist: six
